scrapy_qos/__init__.py
scrapy_qos/qos.py
scrapy_qos-0.0.2.dist-info/METADATA
scrapy_qos-0.0.2.dist-info/WHEEL
scrapy_qos-0.0.2.dist-info/top_level.txt
scrapy_qos-0.0.2.dist-info/RECORD
