Metadata-Version: 2.1
Name: scrapy-qos
Version: 0.0.2
Summary: implement QOS(TokenBucket) in scrapy download middleware
Home-page: https://gitee.com/hgdsdq/scrapy_qos/tree/master
Author: Caft
Author-email: caft0505@163.com
License: MIT License (MIT)
Keywords: scrapy-qos,scrapy,qos,iops,bps
Classifier: Development Status :: 3 - Alpha
Classifier: Environment :: Console
Classifier: Framework :: Scrapy
Classifier: Topic :: Software Development :: Libraries :: Python Modules
Classifier: Intended Audience :: Developers
Classifier: License :: OSI Approved :: MIT License
Classifier: Natural Language :: English
Classifier: Programming Language :: Python :: 3
Classifier: Programming Language :: Python :: 3.7
Classifier: Programming Language :: Python :: 3.8
Classifier: Programming Language :: Python :: 3.9
Classifier: Programming Language :: Python :: 3.10
Requires-Python: >=3.7
Requires-Dist: asyncio
Requires-Dist: scrapy
